ec/__init__.py
ec/ec.py
EasyCoding-1.0.dist-info/LICENSE
EasyCoding-1.0.dist-info/METADATA
EasyCoding-1.0.dist-info/WHEEL
EasyCoding-1.0.dist-info/top_level.txt
EasyCoding-1.0.dist-info/RECORD
