Metadata-Version: 2.1
Name: EasyCoding
Version: 1.0
Summary: A small api for Python code
Home-page: https://gitee.com/ptstudio/gui
Author: PT Studio
Author-email: jjy1207826398@163.com
License: UNKNOWN
Project-URL: Bug Tracker, https://gitee.com/ptstudio/gui/issues
Platform: UNKNOWN
Classifier: Programming Language :: Python :: 3
Classifier: License :: OSI Approved :: MIT License
Classifier: Operating System :: OS Independent
Requires-Python: >=3.6
License-File: LICENSE
